tracebackSilencer.py
tracebacksilencer-0.1.0.dist-info/METADATA
tracebacksilencer-0.1.0.dist-info/WHEEL
tracebacksilencer-0.1.0.dist-info/top_level.txt
tracebacksilencer-0.1.0.dist-info/RECORD
