Metadata-Version: 2.4
Name: tracebackSilencer
Version: 0.1.0
Summary: Silence the anyoing tracebacks
Author-email: Avash <Th3ou1d3x@bloodcircuit.org>
Requires-Python: >=3.0
Requires-Dist: AnsiCoolFORMATING
Requires-Dist: customTraceback
